pytest_wirefracture/__init__.py
pytest_wirefracture/plugin.py
pytest_wirefracture-0.0.1.dist-info/METADATA
pytest_wirefracture-0.0.1.dist-info/WHEEL
pytest_wirefracture-0.0.1.dist-info/entry_points.txt
pytest_wirefracture-0.0.1.dist-info/top_level.txt
pytest_wirefracture-0.0.1.dist-info/RECORD
