Metadata-Version: 2.4
Name: pytest-wirefracture
Version: 0.0.1
Summary: Pytest fixtures for wirefracture
License: MIT
Requires-Python: >=3.8
